alu8/rtl/alu8.v
module alu8(
    input  [7:0] A,
    input  [7:0] B,
    input  [2:0] opcode,
    output reg [7:0] result,
    output reg carry
);

always @(*)
begin
    carry = 1'b0;

    case(opcode)

        3'b000: begin        // ADD
            {carry,result} = A + B;
        end

        3'b001: begin        // SUB
            result = A - B;
        end

        3'b010: begin        // AND
            result = A & B;
        end

        3'b011: begin        // OR
            result = A | B;
        end

        3'b100: begin        // XOR
            result = A ^ B;
        end

        3'b101: begin        // NOT A
            result = ~A;
        end

        3'b110: begin        // SHIFT LEFT
            result = A << 1;
        end

        3'b111: begin        // SHIFT RIGHT
            result = A >> 1;
        end

        default: begin
            result = 8'b0;
        end

    endcase
end

endmodule

alu8/test_bench/alu8_tb.v
`timescale 1ns/1ps

module alu8_tb;

reg [7:0] A;
reg [7:0] B;
reg [2:0] opcode;

wire [7:0] result;
wire carry;
    

alu8 DUT(
    .A(A),
    .B(B),
    .opcode(opcode),
    .result(result),
    .carry(carry)
);


initial begin

    // VCD file for GTKWave
    $dumpfile("alu.vcd");
    $dumpvars(0,alu8_tb);


    $monitor("Time=%0t A=%b B=%b OP=%b RESULT=%b CARRY=%b",
              $time,A,B,opcode,result,carry);


    A = 8'd10;
    B = 8'd5;


    opcode = 3'b000; #10; // ADD
    opcode = 3'b001; #10; // SUB
    opcode = 3'b010; #10; // AND
    opcode = 3'b011; #10; // OR
    opcode = 3'b100; #10; // XOR
    opcode = 3'b101; #10; // NOT
    opcode = 3'b110; #10; // SHIFT LEFT
    opcode = 3'b111; #10; // SHIFT RIGHT


    $finish;

end

endmodule

alu8/simulation/alu.vcd
$date
	Tue Jul 28 23:59:01 2026
$end
$version
	Icarus Verilog
$end
$timescale
	1ps
$end
$scope module alu8_tb $end
$var wire 8 ! result [7:0] $end
$var wire 1 " carry $end
$var reg 8 # A [7:0] $end
$var reg 8 $ B [7:0] $end
$var reg 3 % opcode [2:0] $end
$scope module DUT $end
$var wire 8 & A [7:0] $end
$var wire 8 ' B [7:0] $end
$var wire 3 ( opcode [2:0] $end
$var reg 1 " carry $end
$var reg 8 ) result [7:0] $end
$upscope $end
$upscope $end
$enddefinitions $end
$comment Show the parameter values. $end
$dumpall
$end
#0
$dumpvars
b1111 )
b0 (
b101 '
b1010 &
b0 %
b101 $
b1010 #
0"
b1111 !
$end
#10000
b101 !
b101 )
b1 %
b1 (
#20000
b0 !
b0 )
b10 %
b10 (
#30000
b1111 !
b1111 )
b11 %
b11 (
#40000
b100 %
b100 (
#50000
b11110101 !
b11110101 )
b101 %
b101 (
#60000
b10100 !
b10100 )
b110 %
b110 (
#70000
b101 !
b101 )
b111 %
b111 (
